wgse/third_party/VERSION.py
wgse/third_party/__init__.py
wgse/third_party/bcftools.exe
wgse/third_party/bgzip.exe
wgse/third_party/bwa.exe
wgse/third_party/htsfile.exe
wgse/third_party/minimap2.exe
wgse/third_party/msys-2.0.dll
wgse/third_party/msys-bz2-1.dll
wgse/third_party/msys-lzma-5.dll
wgse/third_party/msys-ncursesw6.dll
wgse/third_party/msys-z.dll
wgse/third_party/samtools.exe
wgse/third_party/tabix.exe
WGSE_NG_3rd_party-0.0.4.dist-info/METADATA
WGSE_NG_3rd_party-0.0.4.dist-info/WHEEL
WGSE_NG_3rd_party-0.0.4.dist-info/top_level.txt
WGSE_NG_3rd_party-0.0.4.dist-info/RECORD
