Metadata-Version: 2.1
Name: WGSE-NG-3rd-party
Version: 0.0.4
Summary: Whole Genome Sequencing data manipulation tool
Author-email: chaplin89 <unavailable@wgse-ng.com>
Project-URL: homepage, https://github.com/WGSE-NG/External
Project-URL: Repository, https://github.com/WGSE-NG/External
Project-URL: Documentation, https://wgse-ng.readthedocs.io/en/latest/
Project-URL: Issues, https://github.com/WGSE-NG/External/issues
Project-URL: Changelog, https://github.com/WGSE-NG/External/releases
Keywords: bioinformatics
Classifier: Development Status :: 1 - Planning
Classifier: Intended Audience :: Developers
Classifier: Intended Audience :: Science/Research
Classifier: License :: OSI Approved :: BSD License
Classifier: License :: OSI Approved :: MIT License
Classifier: Operating System :: OS Independent
Classifier: Programming Language :: Python :: 3.12
Classifier: Topic :: Scientific/Engineering :: Bio-Informatics
